design.sv
module fifo_sync
    // Parameters section
    #( parameter FIFO_DEPTH = 8,
	   parameter DATA_WIDTH = 32)
    // Ports section   
	(input clk, 
     input rst_n,
     input cs,     // chip select	 
     input wr_en, 
     input rd_en, 
     input [DATA_WIDTH-1:0] data_in, 
     output reg [DATA_WIDTH-1:0] data_out, 
	 output empty,
	 output full); 

  localparam FIFO_DEPTH_LOG = $clog2(FIFO_DEPTH);// if fifo_depth is 8 : this gives you 3 as value
	
    // Declare a by-dimensional array to store the data
  reg [DATA_WIDTH-1:0] fifo [0:FIFO_DEPTH-1];// depth 8 => [0:7] 32 bit elements
	
	// Wr/Rd pointer have 1 extra bits at MSB
  reg [FIFO_DEPTH_LOG:0] write_pointer;//3:0 : 4 bits
  reg [FIFO_DEPTH_LOG:0] read_pointer;//3:0 : 4 bits

  //write
    always @(posedge clk or negedge rst_n) 
      begin
      if(!rst_n)//rst =0 system reset happens
		    write_pointer <= 0;
      else if (cs && wr_en && !full) begin
          fifo[write_pointer[FIFO_DEPTH_LOG-1:0]] <= data_in;
	       write_pointer <= write_pointer + 1'b1;
      end
      end
  
	//read
	always @(posedge clk or negedge rst_n) 
      begin
	    if(!rst_n)
		    read_pointer <= 0;
      else if (cs && rd_en && !empty) begin
          	data_out <= fifo[read_pointer[FIFO_DEPTH_LOG-1:0]];
	        read_pointer <= read_pointer + 1'b1;
      end
	end
	
	// Declare the empty/full logic
    assign empty = (read_pointer == write_pointer);
	assign full  = (read_pointer == {~write_pointer[FIFO_DEPTH_LOG], write_pointer[FIFO_DEPTH_LOG-1:0]});

  
  /*
    always @(posedge clk) begin
	    if (cs && wr_en && !full)
	        fifo[write_pointer[FIFO_DEPTH_LOG-1:0]] <= data_in;
	end
	
	always @(posedge clk or negedge rst_n) begin
	    if (!rst_n)
		    data_out <= 0;
		else if (cs && rd_en && !empty)
	        data_out <= fifo[read_pointer[FIFO_DEPTH_LOG-1:0]];
	end
*/
endmodule

testbench.sv
`timescale 1ns/1ns
module tb_fifo_sync();
	
	// Testbench variables
	parameter FIFO_DEPTH = 8;
	parameter DATA_WIDTH = 32;
    reg clk = 0; 
    reg rst_n;
    reg cs;	 
    reg wr_en;
    reg rd_en;
    reg [DATA_WIDTH-1:0] data_in;
    wire [DATA_WIDTH-1:0] data_out;
	wire empty;
	wire full;
	
    integer i;
	
	// Instantiate the DUT
	fifo_sync 
	    #(.FIFO_DEPTH(FIFO_DEPTH),
          .DATA_WIDTH(DATA_WIDTH))
        dut
  	    (.clk     (clk     ), 
         .rst_n   (rst_n   ),
         .cs      (cs      ),	 
         .wr_en   (wr_en   ), 
         .rd_en   (rd_en   ), 
         .data_in (data_in ), 
         .data_out(data_out), 
	     .empty   (empty   ),
	     .full    (full    ));

  	// Create the clock signal
	always begin #5 clk = ~clk; end
  
    task write_data(input [DATA_WIDTH-1:0] d_in);
	    begin
		    @(posedge clk); // sync to positive edge of clock
			cs = 1; wr_en = 1;
			data_in = d_in;
			$display($time, " write_data data_in = %0d", data_in);
			@(posedge clk);
		    cs = 1; wr_en = 0;
		end
	endtask
	
	task read_data();
	    begin
		    @(posedge clk);  // sync to positive edge of clock
			cs = 1; rd_en = 1;
			@(posedge clk);
			//#1;
		    $display($time, " read_data data_out = %0d", data_out);
		    cs = 1; rd_en = 0;
		end
	endtask
	

	
    // Create stimulus	  
    initial begin
	    #1; 
		rst_n = 0; rd_en = 0; wr_en = 0;
		
        @(posedge clk) 
		rst_n = 1;
		$display($time, "\n SCENARIO 1");
		write_data(1);
		write_data(10);
      
		write_data(100);
      
		read_data();
      
		read_data();
      
		read_data();
      
		//read_data();
		
        $display($time, "\n SCENARIO 2");
		for (i=0; i<FIFO_DEPTH; i=i+1) begin
		    write_data(2**i);
			read_data();        
		end

        $display($time, "\n SCENARIO 3");		
		for (i=0; i<=FIFO_DEPTH; i=i+1) begin
		    write_data(2**i);
		end
		
		for (i=0; i<FIFO_DEPTH; i=i+1) begin
			read_data();
		end
		
	    #40 $finish;
	end
  
  initial begin
    $dumpfile("dump.vcd"); $dumpvars;
  end
endmodule

dump.vcd
$date
	Mon Jul 20 22:52:31 2026
$end
$version
	Icarus Verilog
$end
$timescale
	1ns
$end
$scope module tb_fifo_sync $end
$var wire 1 ! full $end
$var wire 1 " empty $end
$var wire 32 # data_out [31:0] $end
$var parameter 32 $ DATA_WIDTH $end
$var parameter 32 % FIFO_DEPTH $end
$var reg 1 & clk $end
$var reg 1 ' cs $end
$var reg 32 ( data_in [31:0] $end
$var reg 1 ) rd_en $end
$var reg 1 * rst_n $end
$var reg 1 + wr_en $end
$var integer 32 , i [31:0] $end
$scope module dut $end
$var wire 1 & clk $end
$var wire 1 ' cs $end
$var wire 32 - data_in [31:0] $end
$var wire 1 ) rd_en $end
$var wire 1 * rst_n $end
$var wire 1 + wr_en $end
$var wire 1 ! full $end
$var wire 1 " empty $end
$var parameter 32 . DATA_WIDTH $end
$var parameter 32 / FIFO_DEPTH $end
$var parameter 32 0 FIFO_DEPTH_LOG $end
$var reg 32 1 data_out [31:0] $end
$var reg 4 2 read_pointer [3:0] $end
$var reg 4 3 write_pointer [3:0] $end
$upscope $end
$scope task read_data $end
$upscope $end
$scope task write_data $end
$var reg 32 4 d_in [31:0] $end
$upscope $end
$upscope $end
$enddefinitions $end
$comment Show the parameter values. $end
$dumpall
b11 0
b1000 /
b100000 .
b1000 %
b100000 $
$end
#0
$dumpvars
bx 4
bx 3
bx 2
bx 1
bx -
bx ,
x+
x*
x)
bx (
x'
0&
bx #
x"
x!
$end
#1
0!
1"
b0 3
b0 2
0+
0)
0*
#5
b1 4
1*
1&
#10
0&
#15
0"
b1 3
b1 (
b1 -
1+
1'
1&
#20
0&
#25
b1010 4
0+
1&
#30
0&
#35
b10 3
b1010 (
b1010 -
1+
1&
#40
0&
#45
b1100100 4
0+
1&
#50
0&
#55
b11 3
b1100100 (
b1100100 -
1+
1&
#60
0&
#65
0+
1&
#70
0&
#75
b1 2
b1 #
b1 1
1)
1&
#80
0&
#85
0)
1&
#90
0&
#95
b10 2
b1010 #
b1010 1
1)
1&
#100
0&
#105
0)
1&
#110
0&
#115
1"
b11 2
b1100100 #
b1100100 1
1)
1&
#120
0&
#125
b1 4
b0 ,
0)
1&
#130
0&
#135
0"
b100 3
b1 (
b1 -
1+
1&
#140
0&
#145
0+
1&
#150
0&
#155
1"
b100 2
b1 #
b1 1
1)
1&
#160
0&
#165
b10 4
b1 ,
0)
1&
#170
0&
#175
0"
b101 3
b10 (
b10 -
1+
1&
#180
0&
#185
0+
1&
#190
0&
#195
1"
b101 2
b10 #
b10 1
1)
1&
#200
0&
#205
b100 4
b10 ,
0)
1&
#210
0&
#215
0"
b110 3
b100 (
b100 -
1+
1&
#220
0&
#225
0+
1&
#230
0&
#235
1"
b110 2
b100 #
b100 1
1)
1&
#240
0&
#245
b1000 4
b11 ,
0)
1&
#250
0&
#255
0"
b111 3
b1000 (
b1000 -
1+
1&
#260
0&
#265
0+
1&
#270
0&
#275
1"
b111 2
b1000 #
b1000 1
1)
1&
#280
0&
#285
b10000 4
b100 ,
0)
1&
#290
0&
#295
0"
b1000 3
b10000 (
b10000 -
1+
1&
#300
0&
#305
0+
1&
#310
0&
#315
1"
b1000 2
b10000 #
b10000 1
1)
1&
#320
0&
#325
b100000 4
b101 ,
0)
1&
#330
0&
#335
0"
b1001 3
b100000 (
b100000 -
1+
1&
#340
0&
#345
0+
1&
#350
0&
#355
1"
b1001 2
b100000 #
b100000 1
1)
1&
#360
0&
#365
b1000000 4
b110 ,
0)
1&
#370
0&
#375
0"
b1010 3
b1000000 (
b1000000 -
1+
1&
#380
0&
#385
0+
1&
#390
0&
#395
1"
b1010 2
b1000000 #
b1000000 1
1)
1&
#400
0&
#405
b10000000 4
b111 ,
0)
1&
#410
0&
#415
0"
b1011 3
b10000000 (
b10000000 -
1+
1&
#420
0&
#425
0+
1&
#430
0&
#435
1"
b1011 2
b10000000 #
b10000000 1
1)
1&
#440
0&
#445
b1 4
b0 ,
0)
1&
#450
0&
#455
0"
b1100 3
b1 (
b1 -
1+
1&
#460
0&
#465
b10 4
b1 ,
0+
1&
#470
0&
#475
b1101 3
b10 (
b10 -
1+
1&
#480
0&
#485
b100 4
b10 ,
0+
1&
#490
0&
#495
b1110 3
b100 (
b100 -
1+
1&
#500
0&
#505
b1000 4
b11 ,
0+
1&
#510
0&
#515
b1111 3
b1000 (
b1000 -
1+
1&
#520
0&
#525
b10000 4
b100 ,
0+
1&
#530
0&
#535
b0 3
b10000 (
b10000 -
1+
1&
#540
0&
#545
b100000 4
b101 ,
0+
1&
#550
0&
#555
b1 3
b100000 (
b100000 -
1+
1&
#560
0&
#565
b1000000 4
b110 ,
0+
1&
#570
0&
#575
b10 3
b1000000 (
b1000000 -
1+
1&
#580
0&
#585
b10000000 4
b111 ,
0+
1&
#590
0&
#595
1!
b11 3
b10000000 (
b10000000 -
1+
1&
#600
0&
#605
b100000000 4
b1000 ,
0+
1&
#610
0&
#615
b100000000 (
b100000000 -
1+
1&
#620
0&
#625
b0 ,
0+
1&
#630
0&
#635
0!
b1100 2
b1 #
b1 1
1)
1&
#640
0&
#645
b1 ,
0)
1&
#650
0&
#655
b1101 2
b10 #
b10 1
1)
1&
#660
0&
#665
b10 ,
0)
1&
#670
0&
#675
b1110 2
b100 #
b100 1
1)
1&
#680
0&
#685
b11 ,
0)
1&
#690
0&
#695
b1111 2
b1000 #
b1000 1
1)
1&
#700
0&
#705
b100 ,
0)
1&
#710
0&
#715
b0 2
b10000 #
b10000 1
1)
1&
#720
0&
#725
b101 ,
0)
1&
#730
0&
#735
b1 2
b100000 #
b100000 1
1)
1&
#740
0&
#745
b110 ,
0)
1&
#750
0&
#755
b10 2
b1000000 #
b1000000 1
1)
1&
#760
0&
#765
b111 ,
0)
1&
#770
0&
#775
1"
b11 2
b10000000 #
b10000000 1
1)
1&
#780
0&
#785
b1000 ,
0)
1&
